gempipe/.ipynb_checkpoints/__init__-checkpoint.py
gempipe/.ipynb_checkpoints/commons-checkpoint.py
gempipe/.ipynb_checkpoints/flowchart-checkpoint.py
gempipe/__init__.py
gempipe/assets/.ipynb_checkpoints/__init__-checkpoint.py
gempipe/assets/.ipynb_checkpoints/bigg_gprs-checkpoint.csv
gempipe/assets/.ipynb_checkpoints/bigg_proteins-checkpoint.faa
gempipe/assets/.ipynb_checkpoints/biolog_mappings-checkpoint.csv
gempipe/assets/.ipynb_checkpoints/minimal_medium-checkpoint.json
gempipe/assets/.ipynb_checkpoints/tcdb_gprs-checkpoint.csv
gempipe/assets/.ipynb_checkpoints/tcdb_rs-checkpoint.csv
gempipe/assets/.ipynb_checkpoints/universe_gramneg-checkpoint.json
gempipe/assets/.ipynb_checkpoints/universe_grampos-checkpoint.json
gempipe/assets/__init__.py
gempipe/assets/bigg_gprs.csv
gempipe/assets/bigg_proteins.faa
gempipe/assets/bigg_to_others_M.pickle
gempipe/assets/bigg_to_others_R.pickle
gempipe/assets/bigg_to_others_extended_M.pickle
gempipe/assets/bigg_to_others_extended_R.pickle
gempipe/assets/biolog_mappings.csv
gempipe/assets/minimal_medium.json
gempipe/assets/seed_to_others_M.pickle
gempipe/assets/seed_to_others_R.pickle
gempipe/assets/seed_to_others_extended_M.pickle
gempipe/assets/seed_to_others_extended_R.pickle
gempipe/assets/tcdb_gprs.csv
gempipe/assets/tcdb_proteins.dmnd
gempipe/assets/tcdb_rs.csv
gempipe/assets/universe_gramneg.json
gempipe/assets/universe_grampos.json
gempipe/autopilot/.ipynb_checkpoints/__init__-checkpoint.py
gempipe/autopilot/.ipynb_checkpoints/manopt-checkpoint.py
gempipe/autopilot/.ipynb_checkpoints/priogapfiller-checkpoint.py
gempipe/autopilot/__init__.py
gempipe/autopilot/manopt.py
gempipe/autopilot/priogapfiller.py
gempipe/commons.py
gempipe/derive/.ipynb_checkpoints/__init__-checkpoint.py
gempipe/derive/.ipynb_checkpoints/biolog-checkpoint.py
gempipe/derive/.ipynb_checkpoints/filler-checkpoint.py
gempipe/derive/.ipynb_checkpoints/reporting-checkpoint.py
gempipe/derive/.ipynb_checkpoints/screening-checkpoint.py
gempipe-1.38.5.dist-info/LICENSE.txt
gempipe-1.38.5.dist-info/METADATA
gempipe-1.38.5.dist-info/WHEEL
gempipe-1.38.5.dist-info/entry_points.txt
gempipe-1.38.5.dist-info/RECORD
