Metadata-Version: 2.1
Name: gempipe
Version: 1.38.5
Summary: 
License: GNU General Public License v3.0
Author: Gioele Lazzari
Requires-Python: >=3.9
Classifier: License :: Other/Proprietary License
Classifier: Programming Language :: Python :: 3
Classifier: Programming Language :: Python :: 3.9
Classifier: Programming Language :: Python :: 3.10
Classifier: Programming Language :: Python :: 3.11
Classifier: Programming Language :: Python :: 3.12
Requires-Dist: biopython (>=1.80)
Requires-Dist: cobra (>=0.29)
Requires-Dist: ipython (>=8.7.0)
Requires-Dist: matplotlib (>=3.7.0)
Requires-Dist: ncbi-genome-download (>=0.3.3)
Requires-Dist: openpyxl (>=3.1.0)
Requires-Dist: pandas (>=2.0.0)
Requires-Dist: scikit-learn (>=1.3.0)
Requires-Dist: scipy (>=1.10.0)
Requires-Dist: seaborn (>=0.13.0)
